fastapi_globals/__init__.py
fastapi_globals/globals.py
fastapi_globals/py.typed
fastapi_globals-0.2.1.dist-info/licenses/LICENSE
fastapi_globals-0.2.1.dist-info/WHEEL
fastapi_globals-0.2.1.dist-info/METADATA
fastapi_globals-0.2.1.dist-info/RECORD
