Metadata-Version: 2.4
Name: fastapi-globals
Version: 0.2.1
Summary: Use request global variables in FastAPI
Author: TEAM23 GmbH
Author-email: TEAM23 GmbH <info@team23.de>
License-Expression: MIT
License-File: LICENSE
Requires-Dist: fastapi>=0.100,<1.0
Requires-Python: >=3.10
Project-URL: Repository, https://github.com/team23/fastapi-globals
